eqt/__init__.py
eqt/__version__.py
eqt/main.py
eqt/party_a.py
eqt/party_b.py
eqt/protocol.py
eqt/timing.py
eqt/util/__init__.py
eqt/util/exceptions.py
eqt/util/log.py
eqt/util/start.py
rens_eqt-1.5.1.dist-info/LICENSE
rens_eqt-1.5.1.dist-info/METADATA
rens_eqt-1.5.1.dist-info/WHEEL
rens_eqt-1.5.1.dist-info/top_level.txt
rens_eqt-1.5.1.dist-info/RECORD
