Metadata-Version: 2.1
Name: rens-eqt
Version: 1.5.1
Summary: Secure Equality Testing
Home-page: https://gitlab.com/RensOliemans/eqt
Author: Rens Oliemans
Author-email: rens.oliemans@gmail.com
License: MIT
Download-URL: https://gitlab.com/RensOliemans/eqt/-/archive/master/eqt-master.tar.gz
Project-URL: Source, https://gitlab.com/RensOliemans/eqt
Project-URL: Tracker, https://gitlab.com/RensOliemans/eqt/-/issues
Platform: UNKNOWN
Classifier: Development Status :: 5 - Production/Stable
Classifier: License :: OSI Approved :: MIT License
Classifier: Operating System :: OS Independent
Classifier: Programming Language :: Python :: 3.8
Classifier: Topic :: Security
Classifier: Topic :: Security :: Cryptography
Classifier: Intended Audience :: Science/Research
Requires-Python: >=3.8
Requires-Dist: rens-paillier (>=1.2)
